DF/__init__.py
DF/files/Dfiles.py
DF/files/__init__.py
DF/html/Dhtml.py
DF/html/__init__.py
duckyframeworks-0.1.15.dist-info/METADATA
duckyframeworks-0.1.15.dist-info/WHEEL
duckyframeworks-0.1.15.dist-info/top_level.txt
duckyframeworks-0.1.15.dist-info/RECORD
