Metadata-Version: 2.4
Name: DuckyFrameworks
Version: 0.1.15
Summary: La libreria oficial de Ducky (no Duckyngscript) para poder usar Frameworks de manera sencilla y hay mucho de donde escojer
Author: José Pato
Author-email: José Pato <tu_email@example.com>
License: MIT
Requires-Python: >=3.11
Dynamic: author
Dynamic: requires-python
